Jenkinsfile
LICENSE
MANIFEST.in
Makefile
README.md
build.parameters
mypy.ini
pskca.spec
pyproject.toml
setup.cfg
tox.ini
src/pskca/__init__.py
src/pskca/ca.py
src/pskca/certs.py
src/pskca/py.typed
src/pskca/requestor.py
src/pskca/types.py
src/pskca/util.py
src/pskca.egg-info/PKG-INFO
src/pskca.egg-info/SOURCES.txt
src/pskca.egg-info/dependency_links.txt
src/pskca.egg-info/requires.txt
src/pskca.egg-info/top_level.txt
tests/conftest.py
tests/test_protocol.py