Metadata-Version: 2.1
Name: pskca
Version: 0.1.10
Summary: A simple implementation of unauthenticated ECDH
Home-page: https://github.com/Rudd-O/pskca
Author: Manuel Amador (Rudd-O)
Author-email: rudd-o@rudd-o.com
Classifier: Programming Language :: Python :: 3
Classifier: License :: OSI Approved :: GNU Lesser General Public License v2 (LGPLv2)
License-File: LICENSE
